Metadata-Version: 2.1
Name: nbindex-jupyter
Version: 0.2.20
Summary: Javascript based Jupyter Notebook additions (Table of Content, hide code, Figure numbers, ...)
Home-page: https://github.com/l-althueser/nbindex-jupyter
Author: Lutz Althüser
Author-email: coding@l-althueser.de
License: BSD 3-Clause License
Platform: UNKNOWN
Classifier: Programming Language :: Python :: 3
Classifier: Framework :: IPython
Classifier: Framework :: Jupyter
Classifier: License :: OSI Approved :: BSD License
Classifier: Operating System :: OS Independent
